parquet/__init__.py
parquet/constants.py
parquet/ttypes.py
parquet_analyzer/__init__.py
parquet_analyzer/__main__.py
parquet_analyzer/_core.py
parquet_analyzer/_html.py
parquet_analyzer/cli.py
parquet_analyzer/templates/report.html
parquet_analyzer/templates/script.js
parquet_analyzer/templates/style.css
parquet_analyzer/templates/toggle-all.html
parquet_analyzer/templates/sections/columns.html
parquet_analyzer/templates/sections/key-value-metadata.html
parquet_analyzer/templates/sections/raw-footer.html
parquet_analyzer/templates/sections/row-groups.html
parquet_analyzer/templates/sections/schema.html
parquet_analyzer/templates/sections/segments.html
parquet_analyzer/templates/sections/summary.html
parquet_analyzer-0.3.0.dist-info/METADATA
parquet_analyzer-0.3.0.dist-info/WHEEL
parquet_analyzer-0.3.0.dist-info/entry_points.txt
parquet_analyzer-0.3.0.dist-info/licenses/LICENSE
parquet_analyzer-0.3.0.dist-info/RECORD
