Metadata-Version: 2.4
Name: parquet-analyzer
Version: 0.3.0
Summary: Inspect the on-disk layout and metadata of Parquet files.
Project-URL: Homepage, https://github.com/clee704/parquet-analyzer
Project-URL: Issues, https://github.com/clee704/parquet-analyzer/issues
Project-URL: Source, https://github.com/clee704/parquet-analyzer
Author: Chungmin Lee
License: 
License-File: LICENSE
Keywords: data-engineering,debugging,parquet,thrift
Classifier: Development Status :: 3 - Alpha
Classifier: Intended Audience :: Developers
Classifier: License :: OSI Approved :: Apache Software License
Classifier: Programming Language :: Python
Classifier: Programming Language :: Python :: 3
Classifier: Programming Language :: Python :: 3 :: Only
Classifier: Programming Language :: Python :: 3.11
Classifier: Programming Language :: Python :: 3.12
Classifier: Programming Language :: Python :: 3.13
Classifier: Programming Language :: Python :: 3.14
Classifier: Topic :: Software Development :: Debuggers
Classifier: Topic :: System :: Filesystems
Requires-Python: >=3.11
Requires-Dist: jinja2==3.1.6
Requires-Dist: thrift>=0.16
Provides-Extra: dev
Requires-Dist: hatch; extra == 'dev'
Requires-Dist: mypy; extra == 'dev'
Requires-Dist: pyarrow; extra == 'dev'
Requires-Dist: pytest; extra == 'dev'
Requires-Dist: pytest-cov; extra == 'dev'
Requires-Dist: ruff; extra == 'dev'
